pycmf/pycmf.cpython-312-darwin.so
pycmf-0.1.0.dist-info/LICENSE
pycmf-0.1.0.dist-info/METADATA
pycmf-0.1.0.dist-info/WHEEL
pycmf-0.1.0.dist-info/top_level.txt
pycmf-0.1.0.dist-info/RECORD
