Metadata-Version: 2.2
Name: pycmf
Version: 0.1.0
Summary: A Circle Median Filter package for Python
Home-page: https://github.com/mstorath/CircleMedianFilter
Author: Martin Storath
Author-email: martin.storath@thws.de
Classifier: Programming Language :: Python :: 3
Classifier: Operating System :: OS Independent
Requires-Python: >=3.6
License-File: LICENSE
Requires-Dist: numpy
Requires-Dist: pybind11
Dynamic: author
Dynamic: author-email
Dynamic: classifier
Dynamic: description
Dynamic: description-content-type
Dynamic: home-page
Dynamic: requires-dist
Dynamic: requires-python
Dynamic: summary
